word_search_puzzle/__init__.py
word_search_puzzle/algorithms.py
word_search_puzzle/exceptions.py
word_search_puzzle/models.py
word_search_puzzle/utils.py
word_search_puzzle-2.0.1.dist-info/LICENSE
word_search_puzzle-2.0.1.dist-info/METADATA
word_search_puzzle-2.0.1.dist-info/WHEEL
word_search_puzzle-2.0.1.dist-info/top_level.txt
word_search_puzzle-2.0.1.dist-info/RECORD
