Metadata-Version: 2.1
Name: word-search-puzzle
Version: 2.0.1
Summary: Word Search Puzzle Generator
Home-page: https://gitlab.com/kilobaik/word-search-puzzle/tree/master
Author: Mohamad Karam Kassem
Author-email: karam.kass@gmail.com
License: UNKNOWN
Platform: UNKNOWN
Classifier: Programming Language :: Python :: 3
Classifier: License :: OSI Approved :: MIT License
Classifier: Operating System :: OS Independent
Classifier: Topic :: Games/Entertainment :: Puzzle Games
Classifier: Development Status :: 5 - Production/Stable
Requires-Python: >=3.6
